dadjokes/__init__.py
dadjokes/dadjokes.py
dadjokes/joke.py
icanhazdadjoke-1.0.0.dist-info/DESCRIPTION.rst
icanhazdadjoke-1.0.0.dist-info/METADATA
icanhazdadjoke-1.0.0.dist-info/RECORD
icanhazdadjoke-1.0.0.dist-info/WHEEL
icanhazdadjoke-1.0.0.dist-info/metadata.json
icanhazdadjoke-1.0.0.dist-info/top_level.txt
