Metadata-Version: 2.0
Name: icanhazdadjoke
Version: 1.0.0
Summary: A Python API wrapper on https://icanhazdadjoke.com
Home-page: https://github.com/vanakenm/icanhazdadjoke-python
Author: Martin Van Aken
Author-email: martin@joyouscoding.com
License: UNKNOWN
Platform: UNKNOWN
Classifier: Development Status :: 5 - Production/Stable
Classifier: Intended Audience :: Developers
Classifier: License :: OSI Approved :: MIT License
Classifier: Programming Language :: Python :: 2
Classifier: Programming Language :: Python :: 2.7
Requires-Dist: requests
